dictionary/__init__.py
dictionary/dictionary.py
dictionary/exceptions.py
dictionary/data/en/words_A.json
dictionary/data/en/words_B.json
dictionary/data/en/words_C.json
dictionary/data/en/words_D.json
dictionary/data/en/words_E.json
dictionary/data/en/words_F.json
dictionary/data/en/words_G.json
dictionary/data/en/words_H.json
dictionary/data/en/words_I.json
dictionary/data/en/words_J.json
dictionary/data/en/words_K.json
dictionary/data/en/words_L.json
dictionary/data/en/words_M.json
dictionary/data/en/words_N.json
dictionary/data/en/words_O.json
dictionary/data/en/words_P.json
dictionary/data/en/words_Q.json
dictionary/data/en/words_R.json
dictionary/data/en/words_S.json
dictionary/data/en/words_T.json
dictionary/data/en/words_U.json
dictionary/data/en/words_V.json
dictionary/data/en/words_W.json
dictionary/data/en/words_X.json
dictionary/data/en/words_Y.json
dictionary/data/en/words_Z.json
dictionary_en_gcide-0.1.0.dist-info/LICENSE
dictionary_en_gcide-0.1.0.dist-info/METADATA
dictionary_en_gcide-0.1.0.dist-info/WHEEL
dictionary_en_gcide-0.1.0.dist-info/top_level.txt
dictionary_en_gcide-0.1.0.dist-info/RECORD
