Metadata-Version: 2.1
Name: dictionary_en_gcide
Version: 0.1.0
Summary: A Python module for english dictionary lookup, based on gcide
Home-page: https://github.com/leafarlins/dictionary_en_gcide
Author: Rafael Lins
Author-email: leafarlins@gmail.com
Classifier: Programming Language :: Python :: 3
Classifier: License :: OSI Approved :: MIT License
Classifier: Operating System :: OS Independent
Requires-Python: >=3.6
License-File: LICENSE
